addresses/__init__.py
addresses/address.json
artifacts/ERC20Template.json
artifacts/ERC721Factory.json
artifacts/ERC721Template.json
artifacts/__init__.py
artifacts/address.json
artifacts/contracts/__init__.py
artifacts/contracts/communityFee/__init__.py
artifacts/contracts/interfaces/__init__.py
artifacts/contracts/templates/__init__.py
artifacts/contracts/utils/__init__.py
neuradao_contracts-1.0.5.dist-info/METADATA
neuradao_contracts-1.0.5.dist-info/WHEEL
neuradao_contracts-1.0.5.dist-info/top_level.txt
neuradao_contracts-1.0.5.dist-info/RECORD
