Metadata-Version: 2.1
Name: neuradao-contracts
Version: 1.0.5
Summary: 🐳 Ocean Protocol L1 - v4
Home-page: https://github.com/Traybot360/ocean-contracts
Author: leucothia`
Author-email: devops@oceanprotocol.com
Project-URL: Bug Tracker, https://github.com/Traybot360/ocean-contracts/issues
Keywords: neuradao-contracts
Classifier: Development Status :: 3 - Alpha
Classifier: Intended Audience :: Developers
Classifier: License :: OSI Approved :: Apache Software License
Classifier: Natural Language :: English
Classifier: Programming Language :: Python :: 3.6
Requires-Python: >=3.6
